LICENSE
README.md
setup.py
diti/__init__.py
diti/calcs.py
diti/constants.py
diti/diti_interval.py
diti/diti_obj.py
diti/diti_ops.py
diti/part_obj.py
diti/timezones.py
diti/util.py
diti.egg-info/PKG-INFO
diti.egg-info/SOURCES.txt
diti.egg-info/dependency_links.txt
diti.egg-info/requires.txt
diti.egg-info/top_level.txt
test/test_calcs.py
test/test_edit.py
test/test_init.py
test/test_interval.py