Metadata-Version: 2.1
Name: diti
Version: 0.0.4
Summary: diti to reduce your datetime operation pains
Home-page: https://github.com/mujdecisy/diti
Author: mujdecisy
Author-email: mujdecisy@gmail.com
Keywords: python,diti,datetime,timezone
Classifier: Programming Language :: Python :: 3
License-File: LICENSE
